jira2markdown/__init__.py
jira2markdown/elements.py
jira2markdown/main.py
jira2markdown/markup/__init__.py
jira2markdown/markup/advanced.py
jira2markdown/markup/base.py
jira2markdown/markup/headings.py
jira2markdown/markup/images.py
jira2markdown/markup/links.py
jira2markdown/markup/lists.py
jira2markdown/markup/tables.py
jira2markdown/markup/text_breaks.py
jira2markdown/markup/text_effects.py
jira2markdown/parser.py
jira2markdown-0.5.dist-info/LICENSE
jira2markdown-0.5.dist-info/METADATA
jira2markdown-0.5.dist-info/WHEEL
jira2markdown-0.5.dist-info/entry_points.txt
jira2markdown-0.5.dist-info/RECORD
