Metadata-Version: 2.3
Name: jira2markdown
Version: 0.5
Summary: Convert text from JIRA markup to Markdown using parsing expression grammars
License: MIT
Keywords: jira,markdown
Author: Evgeniy Krysanov
Author-email: evgeniy.krysanov@gmail.com
Maintainer: Evgeniy Krysanov
Maintainer-email: evgeniy.krysanov@gmail.com
Requires-Python: >=3.9,<4.0
Classifier: Topic :: Text Processing :: Markup
Classifier: Topic :: Text Processing :: Markup :: Markdown
Classifier: Development Status :: 3 - Alpha
Classifier: Programming Language :: Python :: 3
Classifier: Intended Audience :: Developers
Classifier: License :: OSI Approved :: MIT License
Requires-Dist: pyparsing (>=3)
Project-URL: Repository, https://github.com/catcombo/jira2markdown
